bncode/__init__.py
bncode/bncode.py
test/__init__.py
test/create_n_decode.py
bncode-0.0.4.dist-info/LICENCE.md
bncode-0.0.4.dist-info/METADATA
bncode-0.0.4.dist-info/WHEEL
bncode-0.0.4.dist-info/top_level.txt
bncode-0.0.4.dist-info/RECORD
