Metadata-Version: 2.1
Name: bncode
Version: 0.0.4
Summary: BNcode
Home-page: https://github.com/boon4681/bncode.git
Author: boon4681
Author-email: boon4681dev@gmail.com
License: MIT
Platform: UNKNOWN
Classifier: Programming Language :: Python :: 3
Classifier: License :: OSI Approved :: MIT License
Classifier: Operating System :: OS Independent
License-File: LICENCE.md
Requires-Dist: numpy
Requires-Dist: opencv-python
